setup.py
kais/__init__.py
kais/export.py
kais_export.egg-info/PKG-INFO
kais_export.egg-info/SOURCES.txt
kais_export.egg-info/dependency_links.txt
kais_export.egg-info/requires.txt
kais_export.egg-info/top_level.txt