Metadata-Version: 1.0
Name: kais-export
Version: 0.1.0
Summary: Export account moves to KAIS
Home-page: https://github.com/gisce/kais-export
Author: GISCE-TI, S.L.
Author-email: devel@gisce.net
License: GPLv2
Platform: UNKNOWN
